[{"model": "base.trailer", "pk": 1, "fields": {"plates": "4SA5874", "brand": "Krone", "entry_date": "2017-08-21T12:00:00Z", "end_date": null, "vin_code": "WKESD000000759428", "year": 2017, "entry_mileage": "0", "price": "21100.00"}}, {"model": "base.trailer", "pk": 2, "fields": {"plates": "4SA5875", "brand": "Krone", "entry_date": "2017-08-21T12:00:00Z", "end_date": null, "vin_code": "WKESD000000759424", "year": 2017, "entry_mileage": "0", "price": "21100.00"}}, {"model": "base.trailer", "pk": 3, "fields": {"plates": "9AF1016", "brand": "Krone", "entry_date": "2021-04-12T12:00:00Z", "end_date": null, "vin_code": "WKESD000001053798", "year": 2023, "entry_mileage": "111", "price": "29300.00"}}, {"model": "base.trailer", "pk": 13, "fields": {"plates": "9AF1015", "brand": "Krone", "entry_date": "2023-12-12T00:00:00Z", "end_date": null, "vin_code": "WKESD000001053797", "year": 2023, "entry_mileage": "0", "price": "29300.00"}}, {"model": "base.trailer", "pk": 14, "fields": {"plates": "9AE9464", "brand": "Krone", "entry_date": "2023-07-25T00:00:00Z", "end_date": null, "vin_code": "WKESD000001053671", "year": 2023, "entry_mileage": "501783", "price": "33300.00"}}, {"model": "base.trailer", "pk": 15, "fields": {"plates": "9AE8875", "brand": "Krone", "entry_date": "2023-05-30T00:00:00Z", "end_date": null, "vin_code": "WKESD000001053698", "year": 2023, "entry_mileage": "509829", "price": "33300.00"}}]
